README.md
setup.py
robogercontrib/__init__.py
robogercontrib.android.egg-info/PKG-INFO
robogercontrib.android.egg-info/SOURCES.txt
robogercontrib.android.egg-info/dependency_links.txt
robogercontrib.android.egg-info/requires.txt
robogercontrib.android.egg-info/top_level.txt
robogercontrib/android/__init__.py