Metadata-Version: 2.1
Name: robogercontrib.android
Version: 0.0.3
Summary: roboger android plugin
Home-page: https://github.com/alttch/robogercontrib.android
Author: altertech
Author-email: div@altertech.com
License: UNKNOWN
Platform: UNKNOWN
Classifier: Programming Language :: Python :: 3
Classifier: License :: OSI Approved :: MIT License
Classifier: Operating System :: OS Independent
Requires-Python: >=3.6
